weekly_menu/__init__.py
weekly_menu/job/__init__.py
weekly_menu/job/crawler/__init__.py
weekly_menu/job/crawler/run.py
weekly_menu/job/import_recipes/__init__.py
weekly_menu/job/import_recipes/run.py
weekly_menu/webapp/__init__.py
weekly_menu/webapp/api/__init__.py
weekly_menu/webapp/api/exceptions/__init__.py
weekly_menu/webapp/api/models/__init__.py
weekly_menu/webapp/api/models/base_document.py
weekly_menu/webapp/api/models/config.py
weekly_menu/webapp/api/models/ingredient.py
weekly_menu/webapp/api/models/ingredients_view.py
weekly_menu/webapp/api/models/menu.py
weekly_menu/webapp/api/models/recipe.py
weekly_menu/webapp/api/models/shopping_list.py
weekly_menu/webapp/api/models/user.py
weekly_menu/webapp/api/models/user_preferences.py
weekly_menu/webapp/api/schemas/__init__.py
weekly_menu/webapp/api/schemas/validators.py
weekly_menu/webapp/api/v1/__init__.py
weekly_menu/webapp/api/v1/auth/__init__.py
weekly_menu/webapp/api/v1/auth/controllers.py
weekly_menu/webapp/api/v1/auth/schemas.py
weekly_menu/webapp/api/v1/config/__init__.py
weekly_menu/webapp/api/v1/config/resources.py
weekly_menu/webapp/api/v1/external/__init__.py
weekly_menu/webapp/api/v1/external/controllers.py
weekly_menu/webapp/api/v1/external/schema.py
weekly_menu/webapp/api/v1/ingredients/__init__.py
weekly_menu/webapp/api/v1/ingredients/resources.py
weekly_menu/webapp/api/v1/ingredients/schemas.py
weekly_menu/webapp/api/v1/ingredients_view/__init__.py
weekly_menu/webapp/api/v1/ingredients_view/resources.py
weekly_menu/webapp/api/v1/ingredients_view/schemas.py
weekly_menu/webapp/api/v1/menu/__init__.py
weekly_menu/webapp/api/v1/menu/resources.py
weekly_menu/webapp/api/v1/menu/schemas.py
weekly_menu/webapp/api/v1/recipes/__init__.py
weekly_menu/webapp/api/v1/recipes/resources.py
weekly_menu/webapp/api/v1/recipes/schemas.py
weekly_menu/webapp/api/v1/scrapers/__init__.py
weekly_menu/webapp/api/v1/scrapers/controllers.py
weekly_menu/webapp/api/v1/shopping_list/__init__.py
weekly_menu-0.0.59.dist-info/LICENSE
weekly_menu-0.0.59.dist-info/METADATA
weekly_menu-0.0.59.dist-info/WHEEL
weekly_menu-0.0.59.dist-info/top_level.txt
weekly_menu-0.0.59.dist-info/RECORD
