Metadata-Version: 2.1
Name: weekly-menu
Version: 0.0.59
Summary: Automate your weekly menu with AI
Home-page: https://github.com/andreacioni/weekly-menu
Author: Andrea Cioni
Classifier: Programming Language :: Python :: 3
Classifier: License :: OSI Approved :: GNU General Public License v3 (GPLv3)
Classifier: Operating System :: OS Independent
License-File: LICENSE
